python_rtkit-0.7.2.dist-info/DESCRIPTION.rst
python_rtkit-0.7.2.dist-info/METADATA
python_rtkit-0.7.2.dist-info/RECORD
python_rtkit-0.7.2.dist-info/WHEEL
python_rtkit-0.7.2.dist-info/metadata.json
python_rtkit-0.7.2.dist-info/top_level.txt
rtkit/__init__.py
rtkit/authenticators.py
rtkit/comment.py
rtkit/entities.py
rtkit/errors.py
rtkit/forms.py
rtkit/parser.py
rtkit/resource.py
rtkit/tracker.py
rtkit/tests/__init__.py
rtkit/tests/auth.py
rtkit/tests/parser.py
rtkit/tests/resource.py
rtkit/tests/tkt.py
