Metadata-Version: 1.1
Name: python-rtkit
Version: 0.7.2
Summary: Request Tracker REST Interface
